voice_a/__init__.py
voice_a/voice_a.py
voice_a-0.7.0.dist-info/METADATA
voice_a-0.7.0.dist-info/WHEEL
voice_a-0.7.0.dist-info/top_level.txt
voice_a-0.7.0.dist-info/RECORD
