Metadata-Version: 2.1
Name: voice-a
Version: 0.7.0
Summary: A module for hotword detection and speech-to-text functionality.
Classifier: Development Status :: 3 - Alpha
Classifier: Intended Audience :: Developers
Classifier: License :: OSI Approved :: MIT License
Classifier: Programming Language :: Python :: 3
Classifier: Programming Language :: Python :: 3.8
Requires-Dist: playsound ==1.3.0
Requires-Dist: pvporcupine ==1.9.5
Requires-Dist: PyAudio ==0.2.14
Requires-Dist: pygame ==2.6.0
Requires-Dist: requests ==2.32.3
Requires-Dist: selenium ==4.23.1
Requires-Dist: virtual-aide ==0.6
